AUTHORS
CHANGELOG.txt
DESCRIPTION
LICENSE
MANIFEST.in
README.rst
setup.cfg
setup.py
django_markdown_utils.egg-info/PKG-INFO
django_markdown_utils.egg-info/SOURCES.txt
django_markdown_utils.egg-info/dependency_links.txt
django_markdown_utils.egg-info/requires.txt
django_markdown_utils.egg-info/top_level.txt
markdown_utils/__init__.py
markdown_utils/admin.py
markdown_utils/models.py
markdown_utils/urls.py
markdown_utils/views.py
markdown_utils/templatetags/__init__.py
markdown_utils/templatetags/markdown_utils_tags.py
markdown_utils/tests/.coverage
markdown_utils/tests/.coveragerc
markdown_utils/tests/__init__.py
markdown_utils/tests/markdown_utils_tags_tests.py
markdown_utils/tests/runtests.py
markdown_utils/tests/south_settings.py
markdown_utils/tests/test_settings.py
markdown_utils/tests/urls.py
markdown_utils/tests/test_app/__init__.py
markdown_utils/tests/test_app/models.py
markdown_utils/tests/test_app/templates/400.html
markdown_utils/tests/test_app/templates/500.html