Metadata-Version: 1.0
Name: django-markdown-utils
Version: 0.1
Summary: A reusable Django app with some useful markdown utilities
